<design_size title="Design Size Report">
    <item name="Total Instructions per Compilation Phase">
        <table>
            <keys size="4">Phase, Step, Instructions, Description</keys>
            <column name="Compile/Link">, 5015, After all functions are compiled and linked into a single design</column>
            <column name="">, , </column>
            <column name="Unroll/Inline">, , After user unroll and inline pragmas are applied</column>
            <column name="">(1) unroll, 2352, user unroll pragmas are applied</column>
            <column name="">(2) simplification, 1645, simplification of applied user unroll pragmas</column>
            <column name="">(3) inline, 1585, user inline pragmas are applied</column>
            <column name="">(4) simplification, 1585, simplification of applied user inline pragmas</column>
            <column name="">, , </column>
            <column name="Array/Struct">, , After user array partition and struct aggregate/disaggregate pragmas are applied</column>
            <column name="">(1) array partition, 5068, user array partition pragmas are applied</column>
            <column name="">(2) simplification, 3586, simplification of applied user array partition &amp; struct aggregate/disaggregate pragmas</column>
            <column name="">(3) aggregate/disaggregate, 3586, user struct aggregate/disaggregate pragmas are applied</column>
            <column name="">(4) array reshape, 3586, apply array reshape pragmas</column>
            <column name="">(5) access patterns, 3701, array access pattern optmizations</column>
            <column name="">, , </column>
            <column name="Performance">, , After transformations are applied to meet performance pragma targets</column>
            <column name="">(1) loop simplification, 3701, loop and instruction simplification</column>
            <column name="">(2) parallelization, 3586, loops are unrolled or pipelined to meet performance targets</column>
            <column name="">(3) array partition, 3586, arrays are partitioned to meet performance targets</column>
            <column name="">(4) simplification, 3586, simplification of design after performance transformations</column>
            <column name="">, , </column>
            <column name="HW Transforms">, , After hardware transfomations</column>
            <column name="">(1) lowering, 3669, initial conversion to HW specific instructions</column>
            <column name="">(2) optimizations, 3836, high level synthesis optimizations</column>
        </table>
    </item>
    <item name="Instructions per Function for each Compilation Phase">
        <hiertable>
            <header size="7" col0="Function" col1="Location" col2="Compile/Link" col3="Unroll/Inline" col4="Array/Struct" col5="Performance" col6="HW Transforms"/>
            <rows>
                <row id="0" col0="transformer_top" col1="main.cpp:277" col2="5015" col3="1585" col4="3701" col5="3586" col6="3836">
                    <row id="2" col0="fan_out" col1="main.cpp:49" col2="64" col2_disp="  64 (2 calls)" col3="18" col3_disp="  18 (2 calls)" col4="18" col4_disp="  18 (2 calls)" col5="18" col5_disp="  18 (2 calls)" col6="40" col6_disp="  40 (2 calls)"/>
                    <row id="3" col0="fifo" col1="main.cpp:64" col2="108" col2_disp=" 108 (4 calls)" col3="32" col3_disp="  32 (4 calls)" col4="32" col4_disp="  32 (4 calls)" col5="32" col5_disp="  32 (4 calls)" col6="68" col6_disp="  68 (4 calls)"/>
                    <row id="1" col0="stateful_norm" col1="main.cpp:77" col2="884" col2_disp=" 884 (2 calls)" col3="106" col3_disp=" 106 (2 calls)" col4="200" col4_disp=" 200 (2 calls)" col5="166" col5_disp=" 166 (2 calls)" col6="192" col6_disp=" 192 (2 calls)">
                        <row id="9" col0="unpack_beat" col1="main.cpp:27" col2="314" col2_disp=" 314 (2 calls)" col3="" col4="" col5="" col6=""/>
                        <row id="6" col0="pack_beat" col1="main.cpp:35" col2="326" col2_disp=" 326 (2 calls)" col3="" col4="" col5="" col6=""/>
                    </row>
                    <row id="7" col0="gemm" col1="main.cpp:129" col2="1804" col2_disp="1,804 (4 calls)" col3="1000" col3_disp="1,000 (4 calls)" col4="2984" col4_disp="2,984 (4 calls)" col5="2920" col5_disp="2,920 (4 calls)" col6="2972" col6_disp="2,972 (4 calls)">
                        <row id="9" col0="unpack_beat" col1="main.cpp:27" col2="628" col2_disp=" 628 (4 calls)" col3="" col4="" col5="" col6=""/>
                        <row id="6" col0="pack_beat" col1="main.cpp:35" col2="652" col2_disp=" 652 (4 calls)" col3="" col4="" col5="" col6=""/>
                    </row>
                    <row id="4" col0="stateful_softmax" col1="main.cpp:177" col2="471" col3="294" col4="272" col5="255" col6="268">
                        <row id="9" col0="unpack_beat" col1="main.cpp:27" col2="157" col3="" col4="" col5="" col6=""/>
                        <row id="6" col0="pack_beat" col1="main.cpp:35" col2="163" col3="" col4="" col5="" col6=""/>
                    </row>
                    <row id="5" col0="alu_add" col1="main.cpp:252" col2="1140" col2_disp="1,140 (2 calls)" col3="42" col3_disp="  42 (2 calls)" col4="42" col4_disp="  42 (2 calls)" col5="42" col5_disp="  42 (2 calls)" col6="64" col6_disp="  64 (2 calls)">
                        <row id="9" col0="unpack_beat" col1="main.cpp:27" col2="628" col2_disp=" 628 (4 calls)" col3="" col4="" col5="" col6=""/>
                        <row id="6" col0="pack_beat" col1="main.cpp:35" col2="326" col2_disp=" 326 (2 calls)" col3="" col4="" col5="" col6=""/>
                    </row>
                    <row id="8" col0="activation_relu" col1="main.cpp:234" col2="383" col3="19" col4="19" col5="19" col6="28">
                        <row id="9" col0="unpack_beat" col1="main.cpp:27" col2="157" col3="" col4="" col5="" col6=""/>
                        <row id="6" col0="pack_beat" col1="main.cpp:35" col2="163" col3="" col4="" col5="" col6=""/>
                    </row>
                </row>
            </rows>
            <notes/>
        </hiertable>
    </item>
    <item name="Design Size Message Settings">
        <table>
            <keys size="3">Message Setting, Value, Description</keys>
            <column name="config_compile -design_size_maximum_warning">100000, Show a warning when total design instructions exceeds this value</column>
        </table>
    </item>
</design_size>
